[{"name": "Quang Trung", "type": "phuong", "slug": "quang-trung", "name_with_type": "Ph\u01b0\u1eddng Quang Trung", "path": "Quang Trung, H\u00e0 Giang, H\u00e0 Giang", "path_with_type": "Ph\u01b0\u1eddng Quang Trung, Th\u00e0nh ph\u1ed1 H\u00e0 Giang, T\u1ec9nh H\u00e0 Giang", "code": "00688", "parent_code": "024"}, {"name": "Tr\u1ea7n Ph\u00fa", "type": "phuong", "slug": "tran-phu", "name_with_type": "Ph\u01b0\u1eddng Tr\u1ea7n Ph\u00fa", "path": "Tr\u1ea7n Ph\u00fa, H\u00e0 Giang, H\u00e0 Giang", "path_with_type": "Ph\u01b0\u1eddng Tr\u1ea7n Ph\u00fa, Th\u00e0nh ph\u1ed1 H\u00e0 Giang, T\u1ec9nh H\u00e0 Giang", "code": "00691", "parent_code": "024"}, {"name": "Ng\u1ecdc H\u00e0", "type": "phuong", "slug": "ngoc-ha", "name_with_type": "Ph\u01b0\u1eddng Ng\u1ecdc H\u00e0", "path": "Ng\u1ecdc H\u00e0, H\u00e0 Giang, H\u00e0 Giang", "path_with_type": "Ph\u01b0\u1eddng Ng\u1ecdc H\u00e0, Th\u00e0nh ph\u1ed1 H\u00e0 Giang, T\u1ec9nh H\u00e0 Giang", "code": "00692", "parent_code": "024"}, {"name": "Nguy\u1ec5n Tr\u00e3i", "type": "phuong", "slug": "nguyen-trai", "name_with_type": "Ph\u01b0\u1eddng Nguy\u1ec5n Tr\u00e3i", "path": "Nguy\u1ec5n Tr\u00e3i, H\u00e0 Giang, H\u00e0 Giang", "path_with_type": "Ph\u01b0\u1eddng Nguy\u1ec5n Tr\u00e3i, Th\u00e0nh ph\u1ed1 H\u00e0 Giang, T\u1ec9nh H\u00e0 Giang", "code": "00694", "parent_code": "024"}, {"name": "Minh Khai", "type": "phuong", "slug": "minh-khai", "name_with_type": "Ph\u01b0\u1eddng Minh Khai", "path": "Minh Khai, H\u00e0 Giang, H\u00e0 Giang", "path_with_type": "Ph\u01b0\u1eddng Minh Khai, Th\u00e0nh ph\u1ed1 H\u00e0 Giang, T\u1ec9nh H\u00e0 Giang", "code": "00697", "parent_code": "024"}, {"name": "Ng\u1ecdc \u0110\u01b0\u1eddng", "type": "xa", "slug": "ngoc-duong", "name_with_type": "X\u00e3 Ng\u1ecdc \u0110\u01b0\u1eddng", "path": "Ng\u1ecdc \u0110\u01b0\u1eddng, H\u00e0 Giang, H\u00e0 Giang", "path_with_type": "X\u00e3 Ng\u1ecdc \u0110\u01b0\u1eddng, Th\u00e0nh ph\u1ed1 H\u00e0 Giang, T\u1ec9nh H\u00e0 Giang", "code": "00700", "parent_code": "024"}, {"name": "Ph\u01b0\u01a1ng \u0110\u1ed9", "type": "xa", "slug": "phuong-do", "name_with_type": "X\u00e3 Ph\u01b0\u01a1ng \u0110\u1ed9", "path": "Ph\u01b0\u01a1ng \u0110\u1ed9, H\u00e0 Giang, H\u00e0 Giang", "path_with_type": "X\u00e3 Ph\u01b0\u01a1ng \u0110\u1ed9, Th\u00e0nh ph\u1ed1 H\u00e0 Giang, T\u1ec9nh H\u00e0 Giang", "code": "00946", "parent_code": "024"}, {"name": "Ph\u01b0\u01a1ng Thi\u1ec7n", "type": "xa", "slug": "phuong-thien", "name_with_type": "X\u00e3 Ph\u01b0\u01a1ng Thi\u1ec7n", "path": "Ph\u01b0\u01a1ng Thi\u1ec7n, H\u00e0 Giang, H\u00e0 Giang", "path_with_type": "X\u00e3 Ph\u01b0\u01a1ng Thi\u1ec7n, Th\u00e0nh ph\u1ed1 H\u00e0 Giang, T\u1ec9nh H\u00e0 Giang", "code": "00949", "parent_code": "024"}]