[{"name": "B\u1ea3o L\u1ea1c", "type": "thi-tran", "slug": "bao-lac", "name_with_type": "Th\u1ecb tr\u1ea5n B\u1ea3o L\u1ea1c", "path": "B\u1ea3o L\u1ea1c, B\u1ea3o L\u1ea1c, Cao B\u1eb1ng", "path_with_type": "Th\u1ecb tr\u1ea5n B\u1ea3o L\u1ea1c, Huy\u1ec7n B\u1ea3o L\u1ea1c, T\u1ec9nh Cao B\u1eb1ng", "code": "01321", "parent_code": "043"}, {"name": "C\u1ed1c P\u00e0ng", "type": "xa", "slug": "coc-pang", "name_with_type": "X\u00e3 C\u1ed1c P\u00e0ng", "path": "C\u1ed1c P\u00e0ng, B\u1ea3o L\u1ea1c, Cao B\u1eb1ng", "path_with_type": "X\u00e3 C\u1ed1c P\u00e0ng, Huy\u1ec7n B\u1ea3o L\u1ea1c, T\u1ec9nh Cao B\u1eb1ng", "code": "01324", "parent_code": "043"}, {"name": "Th\u01b0\u1ee3ng H\u00e0", "type": "xa", "slug": "thuong-ha", "name_with_type": "X\u00e3 Th\u01b0\u1ee3ng H\u00e0", "path": "Th\u01b0\u1ee3ng H\u00e0, B\u1ea3o L\u1ea1c, Cao B\u1eb1ng", "path_with_type": "X\u00e3 Th\u01b0\u1ee3ng H\u00e0, Huy\u1ec7n B\u1ea3o L\u1ea1c, T\u1ec9nh Cao B\u1eb1ng", "code": "01327", "parent_code": "043"}, {"name": "C\u00f4 Ba", "type": "xa", "slug": "co-ba", "name_with_type": "X\u00e3 C\u00f4 Ba", "path": "C\u00f4 Ba, B\u1ea3o L\u1ea1c, Cao B\u1eb1ng", "path_with_type": "X\u00e3 C\u00f4 Ba, Huy\u1ec7n B\u1ea3o L\u1ea1c, T\u1ec9nh Cao B\u1eb1ng", "code": "01330", "parent_code": "043"}, {"name": "B\u1ea3o To\u00e0n", "type": "xa", "slug": "bao-toan", "name_with_type": "X\u00e3 B\u1ea3o To\u00e0n", "path": "B\u1ea3o To\u00e0n, B\u1ea3o L\u1ea1c, Cao B\u1eb1ng", "path_with_type": "X\u00e3 B\u1ea3o To\u00e0n, Huy\u1ec7n B\u1ea3o L\u1ea1c, T\u1ec9nh Cao B\u1eb1ng", "code": "01333", "parent_code": "043"}, {"name": "Kh\u00e1nh Xu\u00e2n", "type": "xa", "slug": "khanh-xuan", "name_with_type": "X\u00e3 Kh\u00e1nh Xu\u00e2n", "path": "Kh\u00e1nh Xu\u00e2n, B\u1ea3o L\u1ea1c, Cao B\u1eb1ng", "path_with_type": "X\u00e3 Kh\u00e1nh Xu\u00e2n, Huy\u1ec7n B\u1ea3o L\u1ea1c, T\u1ec9nh Cao B\u1eb1ng", "code": "01336", "parent_code": "043"}, {"name": "Xu\u00e2n Tr\u01b0\u1eddng", "type": "xa", "slug": "xuan-truong", "name_with_type": "X\u00e3 Xu\u00e2n Tr\u01b0\u1eddng", "path": "Xu\u00e2n Tr\u01b0\u1eddng, B\u1ea3o L\u1ea1c, Cao B\u1eb1ng", "path_with_type": "X\u00e3 Xu\u00e2n Tr\u01b0\u1eddng, Huy\u1ec7n B\u1ea3o L\u1ea1c, T\u1ec9nh Cao B\u1eb1ng", "code": "01339", "parent_code": "043"}, {"name": "H\u1ed3ng Tr\u1ecb", "type": "xa", "slug": "hong-tri", "name_with_type": "X\u00e3 H\u1ed3ng Tr\u1ecb", "path": "H\u1ed3ng Tr\u1ecb, B\u1ea3o L\u1ea1c, Cao B\u1eb1ng", "path_with_type": "X\u00e3 H\u1ed3ng Tr\u1ecb, Huy\u1ec7n B\u1ea3o L\u1ea1c, T\u1ec9nh Cao B\u1eb1ng", "code": "01342", "parent_code": "043"}, {"name": "Kim C\u00fac", "type": "xa", "slug": "kim-cuc", "name_with_type": "X\u00e3 Kim C\u00fac", "path": "Kim C\u00fac, B\u1ea3o L\u1ea1c, Cao B\u1eb1ng", "path_with_type": "X\u00e3 Kim C\u00fac, Huy\u1ec7n B\u1ea3o L\u1ea1c, T\u1ec9nh Cao B\u1eb1ng", "code": "01343", "parent_code": "043"}, {"name": "Phan Thanh", "type": "xa", "slug": "phan-thanh", "name_with_type": "X\u00e3 Phan Thanh", "path": "Phan Thanh, B\u1ea3o L\u1ea1c, Cao B\u1eb1ng", "path_with_type": "X\u00e3 Phan Thanh, Huy\u1ec7n B\u1ea3o L\u1ea1c, T\u1ec9nh Cao B\u1eb1ng", "code": "01345", "parent_code": "043"}, {"name": "H\u1ed3ng An", "type": "xa", "slug": "hong-an", "name_with_type": "X\u00e3 H\u1ed3ng An", "path": "H\u1ed3ng An, B\u1ea3o L\u1ea1c, Cao B\u1eb1ng", "path_with_type": "X\u00e3 H\u1ed3ng An, Huy\u1ec7n B\u1ea3o L\u1ea1c, T\u1ec9nh Cao B\u1eb1ng", "code": "01348", "parent_code": "043"}, {"name": "H\u01b0ng \u0110\u1ea1o", "type": "xa", "slug": "hung-dao", "name_with_type": "X\u00e3 H\u01b0ng \u0110\u1ea1o", "path": "H\u01b0ng \u0110\u1ea1o, B\u1ea3o L\u1ea1c, Cao B\u1eb1ng", "path_with_type": "X\u00e3 H\u01b0ng \u0110\u1ea1o, Huy\u1ec7n B\u1ea3o L\u1ea1c, T\u1ec9nh Cao B\u1eb1ng", "code": "01351", "parent_code": "043"}, {"name": "H\u01b0ng Th\u1ecbnh", "type": "xa", "slug": "hung-thinh", "name_with_type": "X\u00e3 H\u01b0ng Th\u1ecbnh", "path": "H\u01b0ng Th\u1ecbnh, B\u1ea3o L\u1ea1c, Cao B\u1eb1ng", "path_with_type": "X\u00e3 H\u01b0ng Th\u1ecbnh, Huy\u1ec7n B\u1ea3o L\u1ea1c, T\u1ec9nh Cao B\u1eb1ng", "code": "01352", "parent_code": "043"}, {"name": "Huy Gi\u00e1p", "type": "xa", "slug": "huy-giap", "name_with_type": "X\u00e3 Huy Gi\u00e1p", "path": "Huy Gi\u00e1p, B\u1ea3o L\u1ea1c, Cao B\u1eb1ng", "path_with_type": "X\u00e3 Huy Gi\u00e1p, Huy\u1ec7n B\u1ea3o L\u1ea1c, T\u1ec9nh Cao B\u1eb1ng", "code": "01354", "parent_code": "043"}, {"name": "\u0110\u00ecnh Ph\u00f9ng", "type": "xa", "slug": "dinh-phung", "name_with_type": "X\u00e3 \u0110\u00ecnh Ph\u00f9ng", "path": "\u0110\u00ecnh Ph\u00f9ng, B\u1ea3o L\u1ea1c, Cao B\u1eb1ng", "path_with_type": "X\u00e3 \u0110\u00ecnh Ph\u00f9ng, Huy\u1ec7n B\u1ea3o L\u1ea1c, T\u1ec9nh Cao B\u1eb1ng", "code": "01357", "parent_code": "043"}, {"name": "S\u01a1n L\u1eadp", "type": "xa", "slug": "son-lap", "name_with_type": "X\u00e3 S\u01a1n L\u1eadp", "path": "S\u01a1n L\u1eadp, B\u1ea3o L\u1ea1c, Cao B\u1eb1ng", "path_with_type": "X\u00e3 S\u01a1n L\u1eadp, Huy\u1ec7n B\u1ea3o L\u1ea1c, T\u1ec9nh Cao B\u1eb1ng", "code": "01359", "parent_code": "043"}, {"name": "S\u01a1n L\u1ed9", "type": "xa", "slug": "son-lo", "name_with_type": "X\u00e3 S\u01a1n L\u1ed9", "path": "S\u01a1n L\u1ed9, B\u1ea3o L\u1ea1c, Cao B\u1eb1ng", "path_with_type": "X\u00e3 S\u01a1n L\u1ed9, Huy\u1ec7n B\u1ea3o L\u1ea1c, T\u1ec9nh Cao B\u1eb1ng", "code": "01360", "parent_code": "043"}]