[{"name": "Y\u00ean L\u1eadp", "type": "thi-tran", "slug": "yen-lap", "name_with_type": "Th\u1ecb tr\u1ea5n Y\u00ean L\u1eadp", "path": "Y\u00ean L\u1eadp, Y\u00ean L\u1eadp, Ph\u00fa Th\u1ecd", "path_with_type": "Th\u1ecb tr\u1ea5n Y\u00ean L\u1eadp, Huy\u1ec7n Y\u00ean L\u1eadp, T\u1ec9nh Ph\u00fa Th\u1ecd", "code": "08290", "parent_code": "234"}, {"name": "M\u1ef9 Lung", "type": "xa", "slug": "my-lung", "name_with_type": "X\u00e3 M\u1ef9 Lung", "path": "M\u1ef9 Lung, Y\u00ean L\u1eadp, Ph\u00fa Th\u1ecd", "path_with_type": "X\u00e3 M\u1ef9 Lung, Huy\u1ec7n Y\u00ean L\u1eadp, T\u1ec9nh Ph\u00fa Th\u1ecd", "code": "08293", "parent_code": "234"}, {"name": "M\u1ef9 L\u01b0\u01a1ng", "type": "xa", "slug": "my-luong", "name_with_type": "X\u00e3 M\u1ef9 L\u01b0\u01a1ng", "path": "M\u1ef9 L\u01b0\u01a1ng, Y\u00ean L\u1eadp, Ph\u00fa Th\u1ecd", "path_with_type": "X\u00e3 M\u1ef9 L\u01b0\u01a1ng, Huy\u1ec7n Y\u00ean L\u1eadp, T\u1ec9nh Ph\u00fa Th\u1ecd", "code": "08296", "parent_code": "234"}, {"name": "L\u01b0\u01a1ng S\u01a1n", "type": "xa", "slug": "luong-son", "name_with_type": "X\u00e3 L\u01b0\u01a1ng S\u01a1n", "path": "L\u01b0\u01a1ng S\u01a1n, Y\u00ean L\u1eadp, Ph\u00fa Th\u1ecd", "path_with_type": "X\u00e3 L\u01b0\u01a1ng S\u01a1n, Huy\u1ec7n Y\u00ean L\u1eadp, T\u1ec9nh Ph\u00fa Th\u1ecd", "code": "08299", "parent_code": "234"}, {"name": "Xu\u00e2n An", "type": "xa", "slug": "xuan-an", "name_with_type": "X\u00e3 Xu\u00e2n An", "path": "Xu\u00e2n An, Y\u00ean L\u1eadp, Ph\u00fa Th\u1ecd", "path_with_type": "X\u00e3 Xu\u00e2n An, Huy\u1ec7n Y\u00ean L\u1eadp, T\u1ec9nh Ph\u00fa Th\u1ecd", "code": "08302", "parent_code": "234"}, {"name": "Xu\u00e2n Vi\u00ean", "type": "xa", "slug": "xuan-vien", "name_with_type": "X\u00e3 Xu\u00e2n Vi\u00ean", "path": "Xu\u00e2n Vi\u00ean, Y\u00ean L\u1eadp, Ph\u00fa Th\u1ecd", "path_with_type": "X\u00e3 Xu\u00e2n Vi\u00ean, Huy\u1ec7n Y\u00ean L\u1eadp, T\u1ec9nh Ph\u00fa Th\u1ecd", "code": "08305", "parent_code": "234"}, {"name": "Xu\u00e2n Th\u1ee7y", "type": "xa", "slug": "xuan-thuy", "name_with_type": "X\u00e3 Xu\u00e2n Th\u1ee7y", "path": "Xu\u00e2n Th\u1ee7y, Y\u00ean L\u1eadp, Ph\u00fa Th\u1ecd", "path_with_type": "X\u00e3 Xu\u00e2n Th\u1ee7y, Huy\u1ec7n Y\u00ean L\u1eadp, T\u1ec9nh Ph\u00fa Th\u1ecd", "code": "08308", "parent_code": "234"}, {"name": "Trung S\u01a1n", "type": "xa", "slug": "trung-son", "name_with_type": "X\u00e3 Trung S\u01a1n", "path": "Trung S\u01a1n, Y\u00ean L\u1eadp, Ph\u00fa Th\u1ecd", "path_with_type": "X\u00e3 Trung S\u01a1n, Huy\u1ec7n Y\u00ean L\u1eadp, T\u1ec9nh Ph\u00fa Th\u1ecd", "code": "08311", "parent_code": "234"}, {"name": "H\u01b0ng Long", "type": "xa", "slug": "hung-long", "name_with_type": "X\u00e3 H\u01b0ng Long", "path": "H\u01b0ng Long, Y\u00ean L\u1eadp, Ph\u00fa Th\u1ecd", "path_with_type": "X\u00e3 H\u01b0ng Long, Huy\u1ec7n Y\u00ean L\u1eadp, T\u1ec9nh Ph\u00fa Th\u1ecd", "code": "08314", "parent_code": "234"}, {"name": "Nga Ho\u00e0ng", "type": "xa", "slug": "nga-hoang", "name_with_type": "X\u00e3 Nga Ho\u00e0ng", "path": "Nga Ho\u00e0ng, Y\u00ean L\u1eadp, Ph\u00fa Th\u1ecd", "path_with_type": "X\u00e3 Nga Ho\u00e0ng, Huy\u1ec7n Y\u00ean L\u1eadp, T\u1ec9nh Ph\u00fa Th\u1ecd", "code": "08317", "parent_code": "234"}, {"name": "\u0110\u1ed3ng L\u1ea1c", "type": "xa", "slug": "dong-lac", "name_with_type": "X\u00e3 \u0110\u1ed3ng L\u1ea1c", "path": "\u0110\u1ed3ng L\u1ea1c, Y\u00ean L\u1eadp, Ph\u00fa Th\u1ecd", "path_with_type": "X\u00e3 \u0110\u1ed3ng L\u1ea1c, Huy\u1ec7n Y\u00ean L\u1eadp, T\u1ec9nh Ph\u00fa Th\u1ecd", "code": "08320", "parent_code": "234"}, {"name": "Th\u01b0\u1ee3ng Long", "type": "xa", "slug": "thuong-long", "name_with_type": "X\u00e3 Th\u01b0\u1ee3ng Long", "path": "Th\u01b0\u1ee3ng Long, Y\u00ean L\u1eadp, Ph\u00fa Th\u1ecd", "path_with_type": "X\u00e3 Th\u01b0\u1ee3ng Long, Huy\u1ec7n Y\u00ean L\u1eadp, T\u1ec9nh Ph\u00fa Th\u1ecd", "code": "08323", "parent_code": "234"}, {"name": "\u0110\u1ed3ng Th\u1ecbnh", "type": "xa", "slug": "dong-thinh", "name_with_type": "X\u00e3 \u0110\u1ed3ng Th\u1ecbnh", "path": "\u0110\u1ed3ng Th\u1ecbnh, Y\u00ean L\u1eadp, Ph\u00fa Th\u1ecd", "path_with_type": "X\u00e3 \u0110\u1ed3ng Th\u1ecbnh, Huy\u1ec7n Y\u00ean L\u1eadp, T\u1ec9nh Ph\u00fa Th\u1ecd", "code": "08326", "parent_code": "234"}, {"name": "Ph\u00fac Kh\u00e1nh", "type": "xa", "slug": "phuc-khanh", "name_with_type": "X\u00e3 Ph\u00fac Kh\u00e1nh", "path": "Ph\u00fac Kh\u00e1nh, Y\u00ean L\u1eadp, Ph\u00fa Th\u1ecd", "path_with_type": "X\u00e3 Ph\u00fac Kh\u00e1nh, Huy\u1ec7n Y\u00ean L\u1eadp, T\u1ec9nh Ph\u00fa Th\u1ecd", "code": "08329", "parent_code": "234"}, {"name": "Minh H\u00f2a", "type": "xa", "slug": "minh-hoa", "name_with_type": "X\u00e3 Minh H\u00f2a", "path": "Minh H\u00f2a, Y\u00ean L\u1eadp, Ph\u00fa Th\u1ecd", "path_with_type": "X\u00e3 Minh H\u00f2a, Huy\u1ec7n Y\u00ean L\u1eadp, T\u1ec9nh Ph\u00fa Th\u1ecd", "code": "08332", "parent_code": "234"}, {"name": "Ng\u1ecdc L\u1eadp", "type": "xa", "slug": "ngoc-lap", "name_with_type": "X\u00e3 Ng\u1ecdc L\u1eadp", "path": "Ng\u1ecdc L\u1eadp, Y\u00ean L\u1eadp, Ph\u00fa Th\u1ecd", "path_with_type": "X\u00e3 Ng\u1ecdc L\u1eadp, Huy\u1ec7n Y\u00ean L\u1eadp, T\u1ec9nh Ph\u00fa Th\u1ecd", "code": "08335", "parent_code": "234"}, {"name": "Ng\u1ecdc \u0110\u1ed3ng", "type": "xa", "slug": "ngoc-dong", "name_with_type": "X\u00e3 Ng\u1ecdc \u0110\u1ed3ng", "path": "Ng\u1ecdc \u0110\u1ed3ng, Y\u00ean L\u1eadp, Ph\u00fa Th\u1ecd", "path_with_type": "X\u00e3 Ng\u1ecdc \u0110\u1ed3ng, Huy\u1ec7n Y\u00ean L\u1eadp, T\u1ec9nh Ph\u00fa Th\u1ecd", "code": "08338", "parent_code": "234"}]