[{"name": "C\u1ea9m Th\u01b0\u1ee3ng", "type": "phuong", "slug": "cam-thuong", "name_with_type": "Ph\u01b0\u1eddng C\u1ea9m Th\u01b0\u1ee3ng", "path": "C\u1ea9m Th\u01b0\u1ee3ng, H\u1ea3i D\u01b0\u01a1ng, H\u1ea3i D\u01b0\u01a1ng", "path_with_type": "Ph\u01b0\u1eddng C\u1ea9m Th\u01b0\u1ee3ng, Th\u00e0nh ph\u1ed1 H\u1ea3i D\u01b0\u01a1ng, T\u1ec9nh H\u1ea3i D\u01b0\u01a1ng", "code": "10507", "parent_code": "288"}, {"name": "B\u00ecnh H\u00e0n", "type": "phuong", "slug": "binh-han", "name_with_type": "Ph\u01b0\u1eddng B\u00ecnh H\u00e0n", "path": "B\u00ecnh H\u00e0n, H\u1ea3i D\u01b0\u01a1ng, H\u1ea3i D\u01b0\u01a1ng", "path_with_type": "Ph\u01b0\u1eddng B\u00ecnh H\u00e0n, Th\u00e0nh ph\u1ed1 H\u1ea3i D\u01b0\u01a1ng, T\u1ec9nh H\u1ea3i D\u01b0\u01a1ng", "code": "10510", "parent_code": "288"}, {"name": "Ng\u1ecdc Ch\u00e2u", "type": "phuong", "slug": "ngoc-chau", "name_with_type": "Ph\u01b0\u1eddng Ng\u1ecdc Ch\u00e2u", "path": "Ng\u1ecdc Ch\u00e2u, H\u1ea3i D\u01b0\u01a1ng, H\u1ea3i D\u01b0\u01a1ng", "path_with_type": "Ph\u01b0\u1eddng Ng\u1ecdc Ch\u00e2u, Th\u00e0nh ph\u1ed1 H\u1ea3i D\u01b0\u01a1ng, T\u1ec9nh H\u1ea3i D\u01b0\u01a1ng", "code": "10513", "parent_code": "288"}, {"name": "Nh\u1ecb Ch\u00e2u", "type": "phuong", "slug": "nhi-chau", "name_with_type": "Ph\u01b0\u1eddng Nh\u1ecb Ch\u00e2u", "path": "Nh\u1ecb Ch\u00e2u, H\u1ea3i D\u01b0\u01a1ng, H\u1ea3i D\u01b0\u01a1ng", "path_with_type": "Ph\u01b0\u1eddng Nh\u1ecb Ch\u00e2u, Th\u00e0nh ph\u1ed1 H\u1ea3i D\u01b0\u01a1ng, T\u1ec9nh H\u1ea3i D\u01b0\u01a1ng", "code": "10514", "parent_code": "288"}, {"name": "Quang Trung", "type": "phuong", "slug": "quang-trung", "name_with_type": "Ph\u01b0\u1eddng Quang Trung", "path": "Quang Trung, H\u1ea3i D\u01b0\u01a1ng, H\u1ea3i D\u01b0\u01a1ng", "path_with_type": "Ph\u01b0\u1eddng Quang Trung, Th\u00e0nh ph\u1ed1 H\u1ea3i D\u01b0\u01a1ng, T\u1ec9nh H\u1ea3i D\u01b0\u01a1ng", "code": "10516", "parent_code": "288"}, {"name": "Nguy\u1ec5n Tr\u00e3i", "type": "phuong", "slug": "nguyen-trai", "name_with_type": "Ph\u01b0\u1eddng Nguy\u1ec5n Tr\u00e3i", "path": "Nguy\u1ec5n Tr\u00e3i, H\u1ea3i D\u01b0\u01a1ng, H\u1ea3i D\u01b0\u01a1ng", "path_with_type": "Ph\u01b0\u1eddng Nguy\u1ec5n Tr\u00e3i, Th\u00e0nh ph\u1ed1 H\u1ea3i D\u01b0\u01a1ng, T\u1ec9nh H\u1ea3i D\u01b0\u01a1ng", "code": "10519", "parent_code": "288"}, {"name": "Ph\u1ea1m Ng\u0169 L\u00e3o", "type": "phuong", "slug": "pham-ngu-lao", "name_with_type": "Ph\u01b0\u1eddng Ph\u1ea1m Ng\u0169 L\u00e3o", "path": "Ph\u1ea1m Ng\u0169 L\u00e3o, H\u1ea3i D\u01b0\u01a1ng, H\u1ea3i D\u01b0\u01a1ng", "path_with_type": "Ph\u01b0\u1eddng Ph\u1ea1m Ng\u0169 L\u00e3o, Th\u00e0nh ph\u1ed1 H\u1ea3i D\u01b0\u01a1ng, T\u1ec9nh H\u1ea3i D\u01b0\u01a1ng", "code": "10522", "parent_code": "288"}, {"name": "Tr\u1ea7n H\u01b0ng \u0110\u1ea1o", "type": "phuong", "slug": "tran-hung-dao", "name_with_type": "Ph\u01b0\u1eddng Tr\u1ea7n H\u01b0ng \u0110\u1ea1o", "path": "Tr\u1ea7n H\u01b0ng \u0110\u1ea1o, H\u1ea3i D\u01b0\u01a1ng, H\u1ea3i D\u01b0\u01a1ng", "path_with_type": "Ph\u01b0\u1eddng Tr\u1ea7n H\u01b0ng \u0110\u1ea1o, Th\u00e0nh ph\u1ed1 H\u1ea3i D\u01b0\u01a1ng, T\u1ec9nh H\u1ea3i D\u01b0\u01a1ng", "code": "10525", "parent_code": "288"}, {"name": "Tr\u1ea7n Ph\u00fa", "type": "phuong", "slug": "tran-phu", "name_with_type": "Ph\u01b0\u1eddng Tr\u1ea7n Ph\u00fa", "path": "Tr\u1ea7n Ph\u00fa, H\u1ea3i D\u01b0\u01a1ng, H\u1ea3i D\u01b0\u01a1ng", "path_with_type": "Ph\u01b0\u1eddng Tr\u1ea7n Ph\u00fa, Th\u00e0nh ph\u1ed1 H\u1ea3i D\u01b0\u01a1ng, T\u1ec9nh H\u1ea3i D\u01b0\u01a1ng", "code": "10528", "parent_code": "288"}, {"name": "Thanh B\u00ecnh", "type": "phuong", "slug": "thanh-binh", "name_with_type": "Ph\u01b0\u1eddng Thanh B\u00ecnh", "path": "Thanh B\u00ecnh, H\u1ea3i D\u01b0\u01a1ng, H\u1ea3i D\u01b0\u01a1ng", "path_with_type": "Ph\u01b0\u1eddng Thanh B\u00ecnh, Th\u00e0nh ph\u1ed1 H\u1ea3i D\u01b0\u01a1ng, T\u1ec9nh H\u1ea3i D\u01b0\u01a1ng", "code": "10531", "parent_code": "288"}, {"name": "T\u00e2n B\u00ecnh", "type": "phuong", "slug": "tan-binh", "name_with_type": "Ph\u01b0\u1eddng T\u00e2n B\u00ecnh", "path": "T\u00e2n B\u00ecnh, H\u1ea3i D\u01b0\u01a1ng, H\u1ea3i D\u01b0\u01a1ng", "path_with_type": "Ph\u01b0\u1eddng T\u00e2n B\u00ecnh, Th\u00e0nh ph\u1ed1 H\u1ea3i D\u01b0\u01a1ng, T\u1ec9nh H\u1ea3i D\u01b0\u01a1ng", "code": "10532", "parent_code": "288"}, {"name": "L\u00ea Thanh Ngh\u1ecb", "type": "phuong", "slug": "le-thanh-nghi", "name_with_type": "Ph\u01b0\u1eddng L\u00ea Thanh Ngh\u1ecb", "path": "L\u00ea Thanh Ngh\u1ecb, H\u1ea3i D\u01b0\u01a1ng, H\u1ea3i D\u01b0\u01a1ng", "path_with_type": "Ph\u01b0\u1eddng L\u00ea Thanh Ngh\u1ecb, Th\u00e0nh ph\u1ed1 H\u1ea3i D\u01b0\u01a1ng, T\u1ec9nh H\u1ea3i D\u01b0\u01a1ng", "code": "10534", "parent_code": "288"}, {"name": "H\u1ea3i T\u00e2n", "type": "phuong", "slug": "hai-tan", "name_with_type": "Ph\u01b0\u1eddng H\u1ea3i T\u00e2n", "path": "H\u1ea3i T\u00e2n, H\u1ea3i D\u01b0\u01a1ng, H\u1ea3i D\u01b0\u01a1ng", "path_with_type": "Ph\u01b0\u1eddng H\u1ea3i T\u00e2n, Th\u00e0nh ph\u1ed1 H\u1ea3i D\u01b0\u01a1ng, T\u1ec9nh H\u1ea3i D\u01b0\u01a1ng", "code": "10537", "parent_code": "288"}, {"name": "T\u1ee9 Minh", "type": "phuong", "slug": "tu-minh", "name_with_type": "Ph\u01b0\u1eddng T\u1ee9 Minh", "path": "T\u1ee9 Minh, H\u1ea3i D\u01b0\u01a1ng, H\u1ea3i D\u01b0\u01a1ng", "path_with_type": "Ph\u01b0\u1eddng T\u1ee9 Minh, Th\u00e0nh ph\u1ed1 H\u1ea3i D\u01b0\u01a1ng, T\u1ec9nh H\u1ea3i D\u01b0\u01a1ng", "code": "10540", "parent_code": "288"}, {"name": "Vi\u1ec7t Ho\u00e0", "type": "phuong", "slug": "viet-hoa", "name_with_type": "Ph\u01b0\u1eddng Vi\u1ec7t Ho\u00e0", "path": "Vi\u1ec7t Ho\u00e0, H\u1ea3i D\u01b0\u01a1ng, H\u1ea3i D\u01b0\u01a1ng", "path_with_type": "Ph\u01b0\u1eddng Vi\u1ec7t Ho\u00e0, Th\u00e0nh ph\u1ed1 H\u1ea3i D\u01b0\u01a1ng, T\u1ec9nh H\u1ea3i D\u01b0\u01a1ng", "code": "10543", "parent_code": "288"}, {"name": "\u00c1i Qu\u1ed1c", "type": "phuong", "slug": "ai-quoc", "name_with_type": "Ph\u01b0\u1eddng \u00c1i Qu\u1ed1c", "path": "\u00c1i Qu\u1ed1c, H\u1ea3i D\u01b0\u01a1ng, H\u1ea3i D\u01b0\u01a1ng", "path_with_type": "Ph\u01b0\u1eddng \u00c1i Qu\u1ed1c, Th\u00e0nh ph\u1ed1 H\u1ea3i D\u01b0\u01a1ng, T\u1ec9nh H\u1ea3i D\u01b0\u01a1ng", "code": "10660", "parent_code": "288"}, {"name": "An Th\u01b0\u1ee3ng", "type": "xa", "slug": "an-thuong", "name_with_type": "X\u00e3 An Th\u01b0\u1ee3ng", "path": "An Th\u01b0\u1ee3ng, H\u1ea3i D\u01b0\u01a1ng, H\u1ea3i D\u01b0\u01a1ng", "path_with_type": "X\u00e3 An Th\u01b0\u1ee3ng, Th\u00e0nh ph\u1ed1 H\u1ea3i D\u01b0\u01a1ng, T\u1ec9nh H\u1ea3i D\u01b0\u01a1ng", "code": "10663", "parent_code": "288"}, {"name": "Nam \u0110\u1ed3ng", "type": "phuong", "slug": "nam-dong", "name_with_type": "Ph\u01b0\u1eddng Nam \u0110\u1ed3ng", "path": "Nam \u0110\u1ed3ng, H\u1ea3i D\u01b0\u01a1ng, H\u1ea3i D\u01b0\u01a1ng", "path_with_type": "Ph\u01b0\u1eddng Nam \u0110\u1ed3ng, Th\u00e0nh ph\u1ed1 H\u1ea3i D\u01b0\u01a1ng, T\u1ec9nh H\u1ea3i D\u01b0\u01a1ng", "code": "10672", "parent_code": "288"}, {"name": "Quy\u1ebft Th\u1eafng", "type": "xa", "slug": "quyet-thang", "name_with_type": "X\u00e3 Quy\u1ebft Th\u1eafng", "path": "Quy\u1ebft Th\u1eafng, H\u1ea3i D\u01b0\u01a1ng, H\u1ea3i D\u01b0\u01a1ng", "path_with_type": "X\u00e3 Quy\u1ebft Th\u1eafng, Th\u00e0nh ph\u1ed1 H\u1ea3i D\u01b0\u01a1ng, T\u1ec9nh H\u1ea3i D\u01b0\u01a1ng", "code": "10822", "parent_code": "288"}, {"name": "Ti\u1ec1n Ti\u1ebfn", "type": "xa", "slug": "tien-tien", "name_with_type": "X\u00e3 Ti\u1ec1n Ti\u1ebfn", "path": "Ti\u1ec1n Ti\u1ebfn, H\u1ea3i D\u01b0\u01a1ng, H\u1ea3i D\u01b0\u01a1ng", "path_with_type": "X\u00e3 Ti\u1ec1n Ti\u1ebfn, Th\u00e0nh ph\u1ed1 H\u1ea3i D\u01b0\u01a1ng, T\u1ec9nh H\u1ea3i D\u01b0\u01a1ng", "code": "10837", "parent_code": "288"}, {"name": "Th\u1ea1ch Kh\u00f4i", "type": "phuong", "slug": "thach-khoi", "name_with_type": "Ph\u01b0\u1eddng Th\u1ea1ch Kh\u00f4i", "path": "Th\u1ea1ch Kh\u00f4i, H\u1ea3i D\u01b0\u01a1ng, H\u1ea3i D\u01b0\u01a1ng", "path_with_type": "Ph\u01b0\u1eddng Th\u1ea1ch Kh\u00f4i, Th\u00e0nh ph\u1ed1 H\u1ea3i D\u01b0\u01a1ng, T\u1ec9nh H\u1ea3i D\u01b0\u01a1ng", "code": "11002", "parent_code": "288"}, {"name": "Li\u00ean H\u1ed3ng", "type": "xa", "slug": "lien-hong", "name_with_type": "X\u00e3 Li\u00ean H\u1ed3ng", "path": "Li\u00ean H\u1ed3ng, H\u1ea3i D\u01b0\u01a1ng, H\u1ea3i D\u01b0\u01a1ng", "path_with_type": "X\u00e3 Li\u00ean H\u1ed3ng, Th\u00e0nh ph\u1ed1 H\u1ea3i D\u01b0\u01a1ng, T\u1ec9nh H\u1ea3i D\u01b0\u01a1ng", "code": "11005", "parent_code": "288"}, {"name": "T\u00e2n H\u01b0ng", "type": "phuong", "slug": "tan-hung", "name_with_type": "Ph\u01b0\u1eddng T\u00e2n H\u01b0ng", "path": "T\u00e2n H\u01b0ng, H\u1ea3i D\u01b0\u01a1ng, H\u1ea3i D\u01b0\u01a1ng", "path_with_type": "Ph\u01b0\u1eddng T\u00e2n H\u01b0ng, Th\u00e0nh ph\u1ed1 H\u1ea3i D\u01b0\u01a1ng, T\u1ec9nh H\u1ea3i D\u01b0\u01a1ng", "code": "11011", "parent_code": "288"}, {"name": "Gia Xuy\u00ean", "type": "xa", "slug": "gia-xuyen", "name_with_type": "X\u00e3 Gia Xuy\u00ean", "path": "Gia Xuy\u00ean, H\u1ea3i D\u01b0\u01a1ng, H\u1ea3i D\u01b0\u01a1ng", "path_with_type": "X\u00e3 Gia Xuy\u00ean, Th\u00e0nh ph\u1ed1 H\u1ea3i D\u01b0\u01a1ng, T\u1ec9nh H\u1ea3i D\u01b0\u01a1ng", "code": "11017", "parent_code": "288"}, {"name": "Ng\u1ecdc S\u01a1n", "type": "xa", "slug": "ngoc-son", "name_with_type": "X\u00e3 Ng\u1ecdc S\u01a1n", "path": "Ng\u1ecdc S\u01a1n, H\u1ea3i D\u01b0\u01a1ng, H\u1ea3i D\u01b0\u01a1ng", "path_with_type": "X\u00e3 Ng\u1ecdc S\u01a1n, Th\u00e0nh ph\u1ed1 H\u1ea3i D\u01b0\u01a1ng, T\u1ec9nh H\u1ea3i D\u01b0\u01a1ng", "code": "11077", "parent_code": "288"}]