[{"name": "Tam Thu\u1eadn", "type": "phuong", "slug": "tam-thuan", "name_with_type": "Ph\u01b0\u1eddng Tam Thu\u1eadn", "path": "Tam Thu\u1eadn, Thanh Kh\u00ea, \u0110\u00e0 N\u1eb5ng", "path_with_type": "Ph\u01b0\u1eddng Tam Thu\u1eadn, Qu\u1eadn Thanh Kh\u00ea, Th\u00e0nh ph\u1ed1 \u0110\u00e0 N\u1eb5ng", "code": "20203", "parent_code": "491"}, {"name": "Thanh Kh\u00ea T\u00e2y", "type": "phuong", "slug": "thanh-khe-tay", "name_with_type": "Ph\u01b0\u1eddng Thanh Kh\u00ea T\u00e2y", "path": "Thanh Kh\u00ea T\u00e2y, Thanh Kh\u00ea, \u0110\u00e0 N\u1eb5ng", "path_with_type": "Ph\u01b0\u1eddng Thanh Kh\u00ea T\u00e2y, Qu\u1eadn Thanh Kh\u00ea, Th\u00e0nh ph\u1ed1 \u0110\u00e0 N\u1eb5ng", "code": "20206", "parent_code": "491"}, {"name": "Thanh Kh\u00ea \u0110\u00f4ng", "type": "phuong", "slug": "thanh-khe-dong", "name_with_type": "Ph\u01b0\u1eddng Thanh Kh\u00ea \u0110\u00f4ng", "path": "Thanh Kh\u00ea \u0110\u00f4ng, Thanh Kh\u00ea, \u0110\u00e0 N\u1eb5ng", "path_with_type": "Ph\u01b0\u1eddng Thanh Kh\u00ea \u0110\u00f4ng, Qu\u1eadn Thanh Kh\u00ea, Th\u00e0nh ph\u1ed1 \u0110\u00e0 N\u1eb5ng", "code": "20207", "parent_code": "491"}, {"name": "Xu\u00e2n H\u00e0", "type": "phuong", "slug": "xuan-ha", "name_with_type": "Ph\u01b0\u1eddng Xu\u00e2n H\u00e0", "path": "Xu\u00e2n H\u00e0, Thanh Kh\u00ea, \u0110\u00e0 N\u1eb5ng", "path_with_type": "Ph\u01b0\u1eddng Xu\u00e2n H\u00e0, Qu\u1eadn Thanh Kh\u00ea, Th\u00e0nh ph\u1ed1 \u0110\u00e0 N\u1eb5ng", "code": "20209", "parent_code": "491"}, {"name": "T\u00e2n Ch\u00ednh", "type": "phuong", "slug": "tan-chinh", "name_with_type": "Ph\u01b0\u1eddng T\u00e2n Ch\u00ednh", "path": "T\u00e2n Ch\u00ednh, Thanh Kh\u00ea, \u0110\u00e0 N\u1eb5ng", "path_with_type": "Ph\u01b0\u1eddng T\u00e2n Ch\u00ednh, Qu\u1eadn Thanh Kh\u00ea, Th\u00e0nh ph\u1ed1 \u0110\u00e0 N\u1eb5ng", "code": "20212", "parent_code": "491"}, {"name": "Ch\u00ednh Gi\u00e1n", "type": "phuong", "slug": "chinh-gian", "name_with_type": "Ph\u01b0\u1eddng Ch\u00ednh Gi\u00e1n", "path": "Ch\u00ednh Gi\u00e1n, Thanh Kh\u00ea, \u0110\u00e0 N\u1eb5ng", "path_with_type": "Ph\u01b0\u1eddng Ch\u00ednh Gi\u00e1n, Qu\u1eadn Thanh Kh\u00ea, Th\u00e0nh ph\u1ed1 \u0110\u00e0 N\u1eb5ng", "code": "20215", "parent_code": "491"}, {"name": "V\u0129nh Trung", "type": "phuong", "slug": "vinh-trung", "name_with_type": "Ph\u01b0\u1eddng V\u0129nh Trung", "path": "V\u0129nh Trung, Thanh Kh\u00ea, \u0110\u00e0 N\u1eb5ng", "path_with_type": "Ph\u01b0\u1eddng V\u0129nh Trung, Qu\u1eadn Thanh Kh\u00ea, Th\u00e0nh ph\u1ed1 \u0110\u00e0 N\u1eb5ng", "code": "20218", "parent_code": "491"}, {"name": "Th\u1ea1c Gi\u00e1n", "type": "phuong", "slug": "thac-gian", "name_with_type": "Ph\u01b0\u1eddng Th\u1ea1c Gi\u00e1n", "path": "Th\u1ea1c Gi\u00e1n, Thanh Kh\u00ea, \u0110\u00e0 N\u1eb5ng", "path_with_type": "Ph\u01b0\u1eddng Th\u1ea1c Gi\u00e1n, Qu\u1eadn Thanh Kh\u00ea, Th\u00e0nh ph\u1ed1 \u0110\u00e0 N\u1eb5ng", "code": "20221", "parent_code": "491"}, {"name": "An Kh\u00ea", "type": "phuong", "slug": "an-khe", "name_with_type": "Ph\u01b0\u1eddng An Kh\u00ea", "path": "An Kh\u00ea, Thanh Kh\u00ea, \u0110\u00e0 N\u1eb5ng", "path_with_type": "Ph\u01b0\u1eddng An Kh\u00ea, Qu\u1eadn Thanh Kh\u00ea, Th\u00e0nh ph\u1ed1 \u0110\u00e0 N\u1eb5ng", "code": "20224", "parent_code": "491"}, {"name": "H\u00f2a Kh\u00ea", "type": "phuong", "slug": "hoa-khe", "name_with_type": "Ph\u01b0\u1eddng H\u00f2a Kh\u00ea", "path": "H\u00f2a Kh\u00ea, Thanh Kh\u00ea, \u0110\u00e0 N\u1eb5ng", "path_with_type": "Ph\u01b0\u1eddng H\u00f2a Kh\u00ea, Qu\u1eadn Thanh Kh\u00ea, Th\u00e0nh ph\u1ed1 \u0110\u00e0 N\u1eb5ng", "code": "20225", "parent_code": "491"}]