[{"name": "\u0110\u0103k \u0110oa", "type": "thi-tran", "slug": "dak-doa", "name_with_type": "Th\u1ecb tr\u1ea5n \u0110\u0103k \u0110oa", "path": "\u0110\u0103k \u0110oa, \u0110\u0103k \u0110oa, Gia Lai", "path_with_type": "Th\u1ecb tr\u1ea5n \u0110\u0103k \u0110oa, Huy\u1ec7n \u0110\u0103k \u0110oa, T\u1ec9nh Gia Lai", "code": "23677", "parent_code": "626"}, {"name": "H\u00e0 \u0110\u00f4ng", "type": "xa", "slug": "ha-dong", "name_with_type": "X\u00e3 H\u00e0 \u0110\u00f4ng", "path": "H\u00e0 \u0110\u00f4ng, \u0110\u0103k \u0110oa, Gia Lai", "path_with_type": "X\u00e3 H\u00e0 \u0110\u00f4ng, Huy\u1ec7n \u0110\u0103k \u0110oa, T\u1ec9nh Gia Lai", "code": "23680", "parent_code": "626"}, {"name": "\u0110\u0103k S\u01a1mei", "type": "xa", "slug": "dak-somei", "name_with_type": "X\u00e3 \u0110\u0103k S\u01a1mei", "path": "\u0110\u0103k S\u01a1mei, \u0110\u0103k \u0110oa, Gia Lai", "path_with_type": "X\u00e3 \u0110\u0103k S\u01a1mei, Huy\u1ec7n \u0110\u0103k \u0110oa, T\u1ec9nh Gia Lai", "code": "23683", "parent_code": "626"}, {"name": "\u0110\u0103k Krong", "type": "xa", "slug": "dak-krong", "name_with_type": "X\u00e3 \u0110\u0103k Krong", "path": "\u0110\u0103k Krong, \u0110\u0103k \u0110oa, Gia Lai", "path_with_type": "X\u00e3 \u0110\u0103k Krong, Huy\u1ec7n \u0110\u0103k \u0110oa, T\u1ec9nh Gia Lai", "code": "23684", "parent_code": "626"}, {"name": "H\u1ea3i Yang", "type": "xa", "slug": "hai-yang", "name_with_type": "X\u00e3 H\u1ea3i Yang", "path": "H\u1ea3i Yang, \u0110\u0103k \u0110oa, Gia Lai", "path_with_type": "X\u00e3 H\u1ea3i Yang, Huy\u1ec7n \u0110\u0103k \u0110oa, T\u1ec9nh Gia Lai", "code": "23686", "parent_code": "626"}, {"name": "Kon Gang", "type": "xa", "slug": "kon-gang", "name_with_type": "X\u00e3 Kon Gang", "path": "Kon Gang, \u0110\u0103k \u0110oa, Gia Lai", "path_with_type": "X\u00e3 Kon Gang, Huy\u1ec7n \u0110\u0103k \u0110oa, T\u1ec9nh Gia Lai", "code": "23689", "parent_code": "626"}, {"name": "H\u00e0 B\u1ea7u", "type": "xa", "slug": "ha-bau", "name_with_type": "X\u00e3 H\u00e0 B\u1ea7u", "path": "H\u00e0 B\u1ea7u, \u0110\u0103k \u0110oa, Gia Lai", "path_with_type": "X\u00e3 H\u00e0 B\u1ea7u, Huy\u1ec7n \u0110\u0103k \u0110oa, T\u1ec9nh Gia Lai", "code": "23692", "parent_code": "626"}, {"name": "Nam Yang", "type": "xa", "slug": "nam-yang", "name_with_type": "X\u00e3 Nam Yang", "path": "Nam Yang, \u0110\u0103k \u0110oa, Gia Lai", "path_with_type": "X\u00e3 Nam Yang, Huy\u1ec7n \u0110\u0103k \u0110oa, T\u1ec9nh Gia Lai", "code": "23695", "parent_code": "626"}, {"name": "K' Dang", "type": "xa", "slug": "k-dang", "name_with_type": "X\u00e3 K' Dang", "path": "K' Dang, \u0110\u0103k \u0110oa, Gia Lai", "path_with_type": "X\u00e3 K' Dang, Huy\u1ec7n \u0110\u0103k \u0110oa, T\u1ec9nh Gia Lai", "code": "23698", "parent_code": "626"}, {"name": "H' Neng", "type": "xa", "slug": "h-neng", "name_with_type": "X\u00e3 H' Neng", "path": "H' Neng, \u0110\u0103k \u0110oa, Gia Lai", "path_with_type": "X\u00e3 H' Neng, Huy\u1ec7n \u0110\u0103k \u0110oa, T\u1ec9nh Gia Lai", "code": "23701", "parent_code": "626"}, {"name": "T\u00e2n B\u00ecnh", "type": "xa", "slug": "tan-binh", "name_with_type": "X\u00e3 T\u00e2n B\u00ecnh", "path": "T\u00e2n B\u00ecnh, \u0110\u0103k \u0110oa, Gia Lai", "path_with_type": "X\u00e3 T\u00e2n B\u00ecnh, Huy\u1ec7n \u0110\u0103k \u0110oa, T\u1ec9nh Gia Lai", "code": "23704", "parent_code": "626"}, {"name": "Glar", "type": "xa", "slug": "glar", "name_with_type": "X\u00e3 Glar", "path": "Glar, \u0110\u0103k \u0110oa, Gia Lai", "path_with_type": "X\u00e3 Glar, Huy\u1ec7n \u0110\u0103k \u0110oa, T\u1ec9nh Gia Lai", "code": "23707", "parent_code": "626"}, {"name": "A D\u01a1k", "type": "xa", "slug": "a-dok", "name_with_type": "X\u00e3 A D\u01a1k", "path": "A D\u01a1k, \u0110\u0103k \u0110oa, Gia Lai", "path_with_type": "X\u00e3 A D\u01a1k, Huy\u1ec7n \u0110\u0103k \u0110oa, T\u1ec9nh Gia Lai", "code": "23710", "parent_code": "626"}, {"name": "Trang", "type": "xa", "slug": "trang", "name_with_type": "X\u00e3 Trang", "path": "Trang, \u0110\u0103k \u0110oa, Gia Lai", "path_with_type": "X\u00e3 Trang, Huy\u1ec7n \u0110\u0103k \u0110oa, T\u1ec9nh Gia Lai", "code": "23713", "parent_code": "626"}, {"name": "HNol", "type": "xa", "slug": "hnol", "name_with_type": "X\u00e3 HNol", "path": "HNol, \u0110\u0103k \u0110oa, Gia Lai", "path_with_type": "X\u00e3 HNol, Huy\u1ec7n \u0110\u0103k \u0110oa, T\u1ec9nh Gia Lai", "code": "23714", "parent_code": "626"}, {"name": "Ia P\u1ebft", "type": "xa", "slug": "ia-pet", "name_with_type": "X\u00e3 Ia P\u1ebft", "path": "Ia P\u1ebft, \u0110\u0103k \u0110oa, Gia Lai", "path_with_type": "X\u00e3 Ia P\u1ebft, Huy\u1ec7n \u0110\u0103k \u0110oa, T\u1ec9nh Gia Lai", "code": "23716", "parent_code": "626"}, {"name": "Ia B\u0103ng", "type": "xa", "slug": "ia-bang", "name_with_type": "X\u00e3 Ia B\u0103ng", "path": "Ia B\u0103ng, \u0110\u0103k \u0110oa, Gia Lai", "path_with_type": "X\u00e3 Ia B\u0103ng, Huy\u1ec7n \u0110\u0103k \u0110oa, T\u1ec9nh Gia Lai", "code": "23719", "parent_code": "626"}]