[{"name": "Kr\u00f4ng Kmar", "type": "thi-tran", "slug": "krong-kmar", "name_with_type": "Th\u1ecb tr\u1ea5n Kr\u00f4ng Kmar", "path": "Kr\u00f4ng Kmar, Kr\u00f4ng B\u00f4ng, \u0110\u1eafk L\u1eafk", "path_with_type": "Th\u1ecb tr\u1ea5n Kr\u00f4ng Kmar, Huy\u1ec7n Kr\u00f4ng B\u00f4ng, T\u1ec9nh \u0110\u1eafk L\u1eafk", "code": "24448", "parent_code": "653"}, {"name": "Dang Kang", "type": "xa", "slug": "dang-kang", "name_with_type": "X\u00e3 Dang Kang", "path": "Dang Kang, Kr\u00f4ng B\u00f4ng, \u0110\u1eafk L\u1eafk", "path_with_type": "X\u00e3 Dang Kang, Huy\u1ec7n Kr\u00f4ng B\u00f4ng, T\u1ec9nh \u0110\u1eafk L\u1eafk", "code": "24451", "parent_code": "653"}, {"name": "C\u01b0 KTy", "type": "xa", "slug": "cu-kty", "name_with_type": "X\u00e3 C\u01b0 KTy", "path": "C\u01b0 KTy, Kr\u00f4ng B\u00f4ng, \u0110\u1eafk L\u1eafk", "path_with_type": "X\u00e3 C\u01b0 KTy, Huy\u1ec7n Kr\u00f4ng B\u00f4ng, T\u1ec9nh \u0110\u1eafk L\u1eafk", "code": "24454", "parent_code": "653"}, {"name": "H\u00f2a Th\u00e0nh", "type": "xa", "slug": "hoa-thanh", "name_with_type": "X\u00e3 H\u00f2a Th\u00e0nh", "path": "H\u00f2a Th\u00e0nh, Kr\u00f4ng B\u00f4ng, \u0110\u1eafk L\u1eafk", "path_with_type": "X\u00e3 H\u00f2a Th\u00e0nh, Huy\u1ec7n Kr\u00f4ng B\u00f4ng, T\u1ec9nh \u0110\u1eafk L\u1eafk", "code": "24457", "parent_code": "653"}, {"name": "H\u00f2a T\u00e2n", "type": "xa", "slug": "hoa-tan", "name_with_type": "X\u00e3 H\u00f2a T\u00e2n", "path": "H\u00f2a T\u00e2n, Kr\u00f4ng B\u00f4ng, \u0110\u1eafk L\u1eafk", "path_with_type": "X\u00e3 H\u00f2a T\u00e2n, Huy\u1ec7n Kr\u00f4ng B\u00f4ng, T\u1ec9nh \u0110\u1eafk L\u1eafk", "code": "24460", "parent_code": "653"}, {"name": "H\u00f2a Phong", "type": "xa", "slug": "hoa-phong", "name_with_type": "X\u00e3 H\u00f2a Phong", "path": "H\u00f2a Phong, Kr\u00f4ng B\u00f4ng, \u0110\u1eafk L\u1eafk", "path_with_type": "X\u00e3 H\u00f2a Phong, Huy\u1ec7n Kr\u00f4ng B\u00f4ng, T\u1ec9nh \u0110\u1eafk L\u1eafk", "code": "24463", "parent_code": "653"}, {"name": "H\u00f2a L\u1ec5", "type": "xa", "slug": "hoa-le", "name_with_type": "X\u00e3 H\u00f2a L\u1ec5", "path": "H\u00f2a L\u1ec5, Kr\u00f4ng B\u00f4ng, \u0110\u1eafk L\u1eafk", "path_with_type": "X\u00e3 H\u00f2a L\u1ec5, Huy\u1ec7n Kr\u00f4ng B\u00f4ng, T\u1ec9nh \u0110\u1eafk L\u1eafk", "code": "24466", "parent_code": "653"}, {"name": "Yang Reh", "type": "xa", "slug": "yang-reh", "name_with_type": "X\u00e3 Yang Reh", "path": "Yang Reh, Kr\u00f4ng B\u00f4ng, \u0110\u1eafk L\u1eafk", "path_with_type": "X\u00e3 Yang Reh, Huy\u1ec7n Kr\u00f4ng B\u00f4ng, T\u1ec9nh \u0110\u1eafk L\u1eafk", "code": "24469", "parent_code": "653"}, {"name": "Ea Trul", "type": "xa", "slug": "ea-trul", "name_with_type": "X\u00e3 Ea Trul", "path": "Ea Trul, Kr\u00f4ng B\u00f4ng, \u0110\u1eafk L\u1eafk", "path_with_type": "X\u00e3 Ea Trul, Huy\u1ec7n Kr\u00f4ng B\u00f4ng, T\u1ec9nh \u0110\u1eafk L\u1eafk", "code": "24472", "parent_code": "653"}, {"name": "Khu\u00ea Ng\u1ecdc \u0110i\u1ec1n", "type": "xa", "slug": "khue-ngoc-dien", "name_with_type": "X\u00e3 Khu\u00ea Ng\u1ecdc \u0110i\u1ec1n", "path": "Khu\u00ea Ng\u1ecdc \u0110i\u1ec1n, Kr\u00f4ng B\u00f4ng, \u0110\u1eafk L\u1eafk", "path_with_type": "X\u00e3 Khu\u00ea Ng\u1ecdc \u0110i\u1ec1n, Huy\u1ec7n Kr\u00f4ng B\u00f4ng, T\u1ec9nh \u0110\u1eafk L\u1eafk", "code": "24475", "parent_code": "653"}, {"name": "C\u01b0 Pui", "type": "xa", "slug": "cu-pui", "name_with_type": "X\u00e3 C\u01b0 Pui", "path": "C\u01b0 Pui, Kr\u00f4ng B\u00f4ng, \u0110\u1eafk L\u1eafk", "path_with_type": "X\u00e3 C\u01b0 Pui, Huy\u1ec7n Kr\u00f4ng B\u00f4ng, T\u1ec9nh \u0110\u1eafk L\u1eafk", "code": "24478", "parent_code": "653"}, {"name": "H\u00f2a S\u01a1n", "type": "xa", "slug": "hoa-son", "name_with_type": "X\u00e3 H\u00f2a S\u01a1n", "path": "H\u00f2a S\u01a1n, Kr\u00f4ng B\u00f4ng, \u0110\u1eafk L\u1eafk", "path_with_type": "X\u00e3 H\u00f2a S\u01a1n, Huy\u1ec7n Kr\u00f4ng B\u00f4ng, T\u1ec9nh \u0110\u1eafk L\u1eafk", "code": "24481", "parent_code": "653"}, {"name": "C\u01b0 Dr\u0103m", "type": "xa", "slug": "cu-dram", "name_with_type": "X\u00e3 C\u01b0 Dr\u0103m", "path": "C\u01b0 Dr\u0103m, Kr\u00f4ng B\u00f4ng, \u0110\u1eafk L\u1eafk", "path_with_type": "X\u00e3 C\u01b0 Dr\u0103m, Huy\u1ec7n Kr\u00f4ng B\u00f4ng, T\u1ec9nh \u0110\u1eafk L\u1eafk", "code": "24484", "parent_code": "653"}, {"name": "Yang Mao", "type": "xa", "slug": "yang-mao", "name_with_type": "X\u00e3 Yang Mao", "path": "Yang Mao, Kr\u00f4ng B\u00f4ng, \u0110\u1eafk L\u1eafk", "path_with_type": "X\u00e3 Yang Mao, Huy\u1ec7n Kr\u00f4ng B\u00f4ng, T\u1ec9nh \u0110\u1eafk L\u1eafk", "code": "24487", "parent_code": "653"}]