[{"name": "V\u0129nh Thanh V\u00e2n", "type": "phuong", "slug": "vinh-thanh-van", "name_with_type": "Ph\u01b0\u1eddng V\u0129nh Thanh V\u00e2n", "path": "V\u0129nh Thanh V\u00e2n, R\u1ea1ch Gi\u00e1, Ki\u00ean Giang", "path_with_type": "Ph\u01b0\u1eddng V\u0129nh Thanh V\u00e2n, Th\u00e0nh ph\u1ed1 R\u1ea1ch Gi\u00e1, T\u1ec9nh Ki\u00ean Giang", "code": "30730", "parent_code": "899"}, {"name": "V\u0129nh Thanh", "type": "phuong", "slug": "vinh-thanh", "name_with_type": "Ph\u01b0\u1eddng V\u0129nh Thanh", "path": "V\u0129nh Thanh, R\u1ea1ch Gi\u00e1, Ki\u00ean Giang", "path_with_type": "Ph\u01b0\u1eddng V\u0129nh Thanh, Th\u00e0nh ph\u1ed1 R\u1ea1ch Gi\u00e1, T\u1ec9nh Ki\u00ean Giang", "code": "30733", "parent_code": "899"}, {"name": "V\u0129nh Quang", "type": "phuong", "slug": "vinh-quang", "name_with_type": "Ph\u01b0\u1eddng V\u0129nh Quang", "path": "V\u0129nh Quang, R\u1ea1ch Gi\u00e1, Ki\u00ean Giang", "path_with_type": "Ph\u01b0\u1eddng V\u0129nh Quang, Th\u00e0nh ph\u1ed1 R\u1ea1ch Gi\u00e1, T\u1ec9nh Ki\u00ean Giang", "code": "30736", "parent_code": "899"}, {"name": "V\u0129nh Hi\u1ec7p", "type": "phuong", "slug": "vinh-hiep", "name_with_type": "Ph\u01b0\u1eddng V\u0129nh Hi\u1ec7p", "path": "V\u0129nh Hi\u1ec7p, R\u1ea1ch Gi\u00e1, Ki\u00ean Giang", "path_with_type": "Ph\u01b0\u1eddng V\u0129nh Hi\u1ec7p, Th\u00e0nh ph\u1ed1 R\u1ea1ch Gi\u00e1, T\u1ec9nh Ki\u00ean Giang", "code": "30739", "parent_code": "899"}, {"name": "V\u0129nh B\u1ea3o", "type": "phuong", "slug": "vinh-bao", "name_with_type": "Ph\u01b0\u1eddng V\u0129nh B\u1ea3o", "path": "V\u0129nh B\u1ea3o, R\u1ea1ch Gi\u00e1, Ki\u00ean Giang", "path_with_type": "Ph\u01b0\u1eddng V\u0129nh B\u1ea3o, Th\u00e0nh ph\u1ed1 R\u1ea1ch Gi\u00e1, T\u1ec9nh Ki\u00ean Giang", "code": "30742", "parent_code": "899"}, {"name": "V\u0129nh L\u1ea1c", "type": "phuong", "slug": "vinh-lac", "name_with_type": "Ph\u01b0\u1eddng V\u0129nh L\u1ea1c", "path": "V\u0129nh L\u1ea1c, R\u1ea1ch Gi\u00e1, Ki\u00ean Giang", "path_with_type": "Ph\u01b0\u1eddng V\u0129nh L\u1ea1c, Th\u00e0nh ph\u1ed1 R\u1ea1ch Gi\u00e1, T\u1ec9nh Ki\u00ean Giang", "code": "30745", "parent_code": "899"}, {"name": "An H\u00f2a", "type": "phuong", "slug": "an-hoa", "name_with_type": "Ph\u01b0\u1eddng An H\u00f2a", "path": "An H\u00f2a, R\u1ea1ch Gi\u00e1, Ki\u00ean Giang", "path_with_type": "Ph\u01b0\u1eddng An H\u00f2a, Th\u00e0nh ph\u1ed1 R\u1ea1ch Gi\u00e1, T\u1ec9nh Ki\u00ean Giang", "code": "30748", "parent_code": "899"}, {"name": "An B\u00ecnh", "type": "phuong", "slug": "an-binh", "name_with_type": "Ph\u01b0\u1eddng An B\u00ecnh", "path": "An B\u00ecnh, R\u1ea1ch Gi\u00e1, Ki\u00ean Giang", "path_with_type": "Ph\u01b0\u1eddng An B\u00ecnh, Th\u00e0nh ph\u1ed1 R\u1ea1ch Gi\u00e1, T\u1ec9nh Ki\u00ean Giang", "code": "30751", "parent_code": "899"}, {"name": "R\u1ea1ch S\u1ecfi", "type": "phuong", "slug": "rach-soi", "name_with_type": "Ph\u01b0\u1eddng R\u1ea1ch S\u1ecfi", "path": "R\u1ea1ch S\u1ecfi, R\u1ea1ch Gi\u00e1, Ki\u00ean Giang", "path_with_type": "Ph\u01b0\u1eddng R\u1ea1ch S\u1ecfi, Th\u00e0nh ph\u1ed1 R\u1ea1ch Gi\u00e1, T\u1ec9nh Ki\u00ean Giang", "code": "30754", "parent_code": "899"}, {"name": "V\u0129nh L\u1ee3i", "type": "phuong", "slug": "vinh-loi", "name_with_type": "Ph\u01b0\u1eddng V\u0129nh L\u1ee3i", "path": "V\u0129nh L\u1ee3i, R\u1ea1ch Gi\u00e1, Ki\u00ean Giang", "path_with_type": "Ph\u01b0\u1eddng V\u0129nh L\u1ee3i, Th\u00e0nh ph\u1ed1 R\u1ea1ch Gi\u00e1, T\u1ec9nh Ki\u00ean Giang", "code": "30757", "parent_code": "899"}, {"name": "V\u0129nh Th\u00f4ng", "type": "phuong", "slug": "vinh-thong", "name_with_type": "Ph\u01b0\u1eddng V\u0129nh Th\u00f4ng", "path": "V\u0129nh Th\u00f4ng, R\u1ea1ch Gi\u00e1, Ki\u00ean Giang", "path_with_type": "Ph\u01b0\u1eddng V\u0129nh Th\u00f4ng, Th\u00e0nh ph\u1ed1 R\u1ea1ch Gi\u00e1, T\u1ec9nh Ki\u00ean Giang", "code": "30760", "parent_code": "899"}, {"name": "Phi Th\u00f4ng", "type": "xa", "slug": "phi-thong", "name_with_type": "X\u00e3 Phi Th\u00f4ng", "path": "Phi Th\u00f4ng, R\u1ea1ch Gi\u00e1, Ki\u00ean Giang", "path_with_type": "X\u00e3 Phi Th\u00f4ng, Th\u00e0nh ph\u1ed1 R\u1ea1ch Gi\u00e1, T\u1ec9nh Ki\u00ean Giang", "code": "30763", "parent_code": "899"}]